ra_utils/__init__.py
ra_utils/apply.py
ra_utils/async_to_sync.py
ra_utils/asyncio_utils.py
ra_utils/attrdict.py
ra_utils/catchtime.py
ra_utils/deprecation.py
ra_utils/dict_map.py
ra_utils/ensure_hashable.py
ra_utils/ensure_single_run.py
ra_utils/generate_uuid.py
ra_utils/headers.py
ra_utils/jinja_filter.py
ra_utils/job_settings.py
ra_utils/lazy_dict.py
ra_utils/load_settings.py
ra_utils/multiple_replace.py
ra_utils/py.typed
ra_utils/semantic_version_type.py
ra_utils/sentry_init.py
ra_utils/strategies.py
ra_utils/structured_url.py
ra_utils/syncable.py
ra_utils/tqdm_wrapper.py
ra_utils/transpose_dict.py
ra_utils-1.14.0.dist-info/LICENSES/MPL-2.0.txt
ra_utils-1.14.0.dist-info/METADATA
ra_utils-1.14.0.dist-info/WHEEL
ra_utils-1.14.0.dist-info/RECORD
